astdispatch.py
setup.py
astdispatch.egg-info/PKG-INFO
astdispatch.egg-info/SOURCES.txt
astdispatch.egg-info/dependency_links.txt
astdispatch.egg-info/requires.txt
astdispatch.egg-info/top_level.txt